ai_course_generator/__init__.py
ai_course_generator/course_generator_agent.py
ai_course_generator/emoji-support.tex
ai_course_generator/generate_course.py
ai_course_generator/mermaid_processor.py
ai_course_generator-0.3.0.dist-info/LICENSE
ai_course_generator-0.3.0.dist-info/METADATA
ai_course_generator-0.3.0.dist-info/WHEEL
ai_course_generator-0.3.0.dist-info/entry_points.txt
ai_course_generator-0.3.0.dist-info/RECORD
