Metadata-Version: 2.3
Name: ai-course-generator
Version: 0.3.0
Summary: An AI-powered course generation tool that creates comprehensive educational content using advanced language models
Author: Raphaël MANSUY
Author-email: raphael.mansuy@gmail.com
Requires-Python: >=3.12,<4.0
Classifier: Programming Language :: Python :: 3
Classifier: Programming Language :: Python :: 3.12
Classifier: Programming Language :: Python :: 3.13
Requires-Dist: aiofiles (>=24.1.0,<25.0.0)
Requires-Dist: anyio (>=4.8.0,<5.0.0)
Requires-Dist: instructor (>=1.7.2,<2.0.0)
Requires-Dist: jinja2 (>=3.1.5,<4.0.0)
Requires-Dist: litellm (>=1.61.20,<2.0.0)
Requires-Dist: loguru (>=0.7.3,<0.8.0)
Requires-Dist: pydantic (>=2.10.6,<3.0.0)
Requires-Dist: pypandoc (>=1.15,<2.0)
Requires-Dist: quantalogic (>=0.61.3,<0.62.0)
Requires-Dist: rich (>=13.9.4,<14.0.0)
Requires-Dist: typer (>=0.15.2,<0.16.0)
